amarillo/__init__.py
amarillo/configuration.py
amarillo/main.py
amarillo/models/Carpool.py
amarillo/models/User.py
amarillo/models/__init__.py
amarillo/plugins/__init__.py
amarillo/routers/__init__.py
amarillo/routers/agency.py
amarillo/routers/carpool.py
amarillo/routers/region.py
amarillo/routers/users.py
amarillo/services/__init__.py
amarillo/services/agencies.py
amarillo/services/carpools.py
amarillo/services/config.py
amarillo/services/mocks.py
amarillo/services/oauth2.py
amarillo/services/passwords.py
amarillo/services/regions.py
amarillo/services/secrets.py
amarillo/services/users.py
amarillo/services/importing/__init__.py
amarillo/services/importing/ride2go.py
amarillo/static/config
amarillo/static/logging.conf
amarillo/static/conf/stop_sources.json
amarillo/static/conf/agency/frank.json
amarillo/static/conf/agency/goflux.json
amarillo/static/conf/agency/mentz.json
amarillo/static/conf/agency/mfdz.json
amarillo/static/conf/agency/mifaz.json
amarillo/static/conf/agency/mvv.json
amarillo/static/conf/agency/ride2go.json
amarillo/static/conf/region/bb.json
amarillo/static/conf/region/bw.json
amarillo/static/conf/region/by.json
amarillo/static/conf/region/nrw.json
amarillo/static/static/css/docs.css
amarillo/static/static/css/theme.css
amarillo/static/static/img/cloud.png
amarillo/static/static/img/favicon.ico
amarillo/static/templates/home/index.html
amarillo/static/templates/shared/layout.html
amarillo/tests/__init__.py
amarillo/tests/no_test_carpool.py
amarillo/tests/sampledata.py
amarillo/tests/test_permissions.py
amarillo/tests/__pycache__/__init__.cpython-39.pyc
amarillo/tests/__pycache__/sampledata.cpython-39.pyc
amarillo/tests/__pycache__/test_permissions.cpython-39-pytest-7.4.0.pyc
amarillo/utils/__init__.py
amarillo/utils/container.py
amarillo/utils/utils.py
amarillo/views/home.py
amarillo-0.0.16a1.dist-info/METADATA
amarillo-0.0.16a1.dist-info/WHEEL
amarillo-0.0.16a1.dist-info/top_level.txt
amarillo-0.0.16a1.dist-info/RECORD
