Metadata-Version: 2.1
Name: amarillo
Version: 0.0.16a1
Summary: Aggregates and enhances carpooling-offers and publishes them as GTFS(-RT)
Keywords: amarillo,ridesharing,carpooling,gtfs,gtfs-rt
Requires-Dist: fastapi[all] ==0.109.0
Requires-Dist: geopandas ==0.14
Requires-Dist: uvicorn[standard] ==0.23.2
Requires-Dist: pydantic[dotenv] ==2.4.2
Requires-Dist: protobuf ==3.20.3
Requires-Dist: starlette ~=0.35
Requires-Dist: requests ==2.31.0
Requires-Dist: pyproj ==3.6.1
Requires-Dist: geojson-pydantic ==1.0.1
Requires-Dist: watchdog ==3.0.0
Requires-Dist: python-jose[cryptography]
Requires-Dist: bcrypt ==4.0.1
Requires-Dist: passlib[bcrypt]
